{
    "configurations": [
        {
            "name": "Win32",
            "includePath": [
                "${workspaceFolder}/**",
                // "C:\\msys\\mingw64\\include\\c++\\14.1.0",
                "${workspaceFolder}/CPP/include",
                "${workspaceFolder}/CPP/cpp-httplib"
                // "C:/msys/ucrt64/include/c++/14.1.0/x86_64-w64-mingw32",
                // "C:/msys/mingw64/**"
            ],
            "defines": [
                "_DEBUG",
                "UNICODE",
                "_UNICODE"
            ],
            "cStandard": "c11",
            "cppStandard": "c++11",
            "intelliSenseMode": "windows-gcc-x64",
            "compilerPath": "C:/msys/ucrt64/bin/g++.exe",
            "compilerArgs": [
                "-lws2_32"
            ]
        }
    ],
    "version": 4
}